Metadata-Version: 1.0
Name: harish-distributions
Version: 0.1
Summary: Gaussian And Binomial distributions
Home-page: UNKNOWN
Author: Harish Chandramohan
Author-email: harishkumarchandra@gmail.com
License: UNKNOWN
Platform: UNKNOWN
